cbx/__init__.py
cbx/constraints.py
cbx/correction.py
cbx/noise.py
cbx/objectives.py
cbx/plotting.py
cbx/regularizers.py
cbx/scheduler.py
cbx/dynamics/__init__.py
cbx/dynamics/adamcbo.py
cbx/dynamics/cbo.py
cbx/dynamics/cbo_memory.py
cbx/dynamics/cbs.py
cbx/dynamics/driftconstrainedcbo.py
cbx/dynamics/hypersurfacecbo.py
cbx/dynamics/mirrorcbo.py
cbx/dynamics/pdyn.py
cbx/dynamics/polarcbo.py
cbx/dynamics/pso.py
cbx/dynamics/regcombinationcbo.py
cbx/utils/__init__.py
cbx/utils/history.py
cbx/utils/objective_handling.py
cbx/utils/particle_init.py
cbx/utils/resampling.py
cbx/utils/success.py
cbx/utils/termination.py
cbx/utils/torch_utils.py
cbx-1.0.1.dist-info/licenses/LICENSE
cbx-1.0.1.dist-info/METADATA
cbx-1.0.1.dist-info/WHEEL
cbx-1.0.1.dist-info/top_level.txt
cbx-1.0.1.dist-info/RECORD
