Metadata-Version: 2.4
Name: cbx
Version: 1.0.1
Summary: CBXpy
Author-email: Tim Roith <tim.roith@desy.de>
Classifier: Programming Language :: Python :: 3
Classifier: License :: OSI Approved :: MIT License
Classifier: Operating System :: OS Independent
Requires-Python: >3.5.2
License-File: LICENSE
Requires-Dist: numpy
Requires-Dist: scipy
Requires-Dist: matplotlib
Provides-Extra: test
Requires-Dist: pytest; extra == "test"
Requires-Dist: torch; extra == "test"
Provides-Extra: torch
Requires-Dist: torch; extra == "torch"
Dynamic: license-file
